correct/__init__.py
correct/requirements.txt
correct/exception/correct_exception.py
correct/funcs/alignment.py
correct/funcs/correction.py
correct/funcs/data_handle.py
correct/logger/logger.py
correct/response/response.py
correct/response/response_code.py
correct/tools/constants.py
correct/tools/min_edit_distance.py
correct/tools/point_handle.py
correct/tools/rectangle_handle.py
correct/tools/str_tools.py
hs_correct-0.0.6.dist-info/METADATA
hs_correct-0.0.6.dist-info/WHEEL
hs_correct-0.0.6.dist-info/top_level.txt
hs_correct-0.0.6.dist-info/RECORD
