Metadata-Version: 2.1
Name: hs_correct
Version: 0.0.6
Summary: hs-correct-module
Home-page: 
Author: zgl
Author-email: 
License: MIT
Keywords: hs-correct-module
Requires-Dist: numpy
Requires-Dist: shapely
Requires-Dist: colorama
